{"success":true,"data":[{"_id":"64b0d1a5d312a30c6981bf2f","name":"KEC.BABELAN"},{"_id":"64b0d1a5d312a30c6981bf32","name":"KEC.BOJONGMANGGU"},{"_id":"64b0d1a5d312a30c6981bf35","name":"KEC.CABANGBUNGIN"},{"_id":"64b0d1a5d312a30c6981bf38","name":"KEC.CIBARUSAH"},{"_id":"64b0d1a5d312a30c6981bf3b","name":"KEC.CIBITUNG"},{"_id":"64b0d1a5d312a30c6981bf3e","name":"KEC.CIKARANG BARAT"},{"_id":"64b0d1a5d312a30c6981bf41","name":"KEC.CIKARANG SELATAN"},{"_id":"64b0d1a5d312a30c6981bf44","name":"KEC.CIKARANG TIMUR"},{"_id":"64b0d1a5d312a30c6981bf47","name":"KEC.CIKARANG UTARA"},{"_id":"64b0d1a5d312a30c6981bf4a","name":"KEC.CIKARANG PUSAT"},{"_id":"64b0d1a5d312a30c6981bf4d","name":"KEC.KARANGBAHAGIA"},{"_id":"64b0d1a5d312a30c6981bf50","name":"KEC.KEDUNGWARINGIN"},{"_id":"64b0d1a5d312a30c6981bf53","name":"KEC.MUARAGEMBONG"},{"_id":"64b0d1a5d312a30c6981bf56","name":"KEC.PEBAYURAN"},{"_id":"64b0d1a5d312a30c6981bf59","name":"KEC.SERANGBARU"},{"_id":"64b0d1a5d312a30c6981bf5c","name":"KEC.SETU"},{"_id":"64b0d1a5d312a30c6981bf5f","name":"KEC.SUKAKARYA"},{"_id":"64b0d1a5d312a30c6981bf62","name":"KEC.SUKATANI"},{"_id":"64b0d1a5d312a30c6981bf65","name":"KEC.SUKAWANGI"},{"_id":"64b0d1a5d312a30c6981bf68","name":"KEC.TAMBELANG"},{"_id":"64b0d1a5d312a30c6981bf6b","name":"KEC.TAMBUN SELATAN"},{"_id":"64b0d1a5d312a30c6981bf6e","name":"KEC.TAMBUN UTARA"},{"_id":"64b0d1a5d312a30c6981bf74","name":"KEC.TARUMAJAYA"}],"message":"Success Get Kecamatan","code":200}